alibabacloud_websitebuild20250429/__init__.py
alibabacloud_websitebuild20250429/client.py
alibabacloud_websitebuild20250429/models/__init__.py
alibabacloud_websitebuild20250429/models/_app_ai_staff.py
alibabacloud_websitebuild20250429/models/_app_instance.py
alibabacloud_websitebuild20250429/models/_app_instance_aggregate.py
alibabacloud_websitebuild20250429/models/_app_instance_profile.py
alibabacloud_websitebuild20250429/models/_app_operate_action.py
alibabacloud_websitebuild20250429/models/_app_operation_address.py
alibabacloud_websitebuild20250429/models/_app_service.py
alibabacloud_websitebuild20250429/models/_app_service_aggregate.py
alibabacloud_websitebuild20250429/models/_app_service_group.py
alibabacloud_websitebuild20250429/models/_app_service_profile.py
alibabacloud_websitebuild20250429/models/_bind_app_domain_request.py
alibabacloud_websitebuild20250429/models/_bind_app_domain_response.py
alibabacloud_websitebuild20250429/models/_bind_app_domain_response_body.py
alibabacloud_websitebuild20250429/models/_create_app_instance_request.py
alibabacloud_websitebuild20250429/models/_create_app_instance_response.py
alibabacloud_websitebuild20250429/models/_create_app_instance_response_body.py
alibabacloud_websitebuild20250429/models/_create_app_instance_shrink_request.py
alibabacloud_websitebuild20250429/models/_create_app_instance_ticket_request.py
alibabacloud_websitebuild20250429/models/_create_app_instance_ticket_response.py
alibabacloud_websitebuild20250429/models/_create_app_instance_ticket_response_body.py
alibabacloud_websitebuild20250429/models/_create_logo_task_request.py
alibabacloud_websitebuild20250429/models/_create_logo_task_response.py
alibabacloud_websitebuild20250429/models/_create_logo_task_response_body.py
alibabacloud_websitebuild20250429/models/_delete_app_domain_certificate_request.py
alibabacloud_websitebuild20250429/models/_delete_app_domain_certificate_response.py
alibabacloud_websitebuild20250429-2.8.3.dist-info/LICENSE
alibabacloud_websitebuild20250429-2.8.3.dist-info/METADATA
alibabacloud_websitebuild20250429-2.8.3.dist-info/WHEEL
alibabacloud_websitebuild20250429-2.8.3.dist-info/top_level.txt
alibabacloud_websitebuild20250429-2.8.3.dist-info/RECORD
